mplunitx/__init__.py
mplunitx/__version__.py
mplunitx/_sisetup.py
mplunitx/number.py
mplunitx/unit.py
mplunitx-0.1.0.dist-info/METADATA
mplunitx-0.1.0.dist-info/WHEEL
mplunitx-0.1.0.dist-info/top_level.txt
mplunitx-0.1.0.dist-info/RECORD
