Metadata-Version: 2.1
Name: mplunitx
Version: 0.1.0
Summary: Units in python strings for matplotlib labels
Author: Adrian Peter Krone
Author-email: adrian.krone@physik.uni-kassel.de
License: "MIT"
Project-URL: docs, https://mplunitx.readthedocs.io/en/latest/,
Project-URL: GitHub, https://github.com/adryyan/mplunitx
Keywords: matplotlib,siunitx,latex
Classifier: Programming Language :: Python :: 3
Classifier: Development Status :: 3 - Alpha
Classifier: Intended Audience :: Education
Classifier: Intended Audience :: Science/Research
Requires-Python: >=3.9
